[{"componentId":5,"drawableId":10,"textureId":0,"price":0,"label":null,"restrictionTags":null},{"componentId":5,"drawableId":11,"textureId":0,"price":0,"label":null,"restrictionTags":null},{"componentId":5,"drawableId":11,"textureId":1,"price":0,"label":null,"restrictionTags":null},{"componentId":5,"drawableId":11,"textureId":2,"price":0,"label":null,"restrictionTags":null},{"componentId":5,"drawableId":11,"textureId":3,"price":0,"label":null,"restrictionTags":null},{"componentId":5,"drawableId":11,"textureId":4,"price":0,"label":null,"restrictionTags":null},{"componentId":5,"drawableId":11,"textureId":5,"price":0,"label":null,"restrictionTags":null},{"componentId":5,"drawableId":11,"textureId":6,"price":0,"label":null,"restrictionTags":null},{"componentId":5,"drawableId":11,"textureId":7,"price":0,"label":null,"restrictionTags":null},{"componentId":5,"drawableId":11,"textureId":8,"price":0,"label":null,"restrictionTags":null},{"componentId":5,"drawableId":11,"textureId":9,"price":0,"label":null,"restrictionTags":null},{"componentId":5,"drawableId":11,"textureId":10,"price":0,"label":null,"restrictionTags":null},{"componentId":5,"drawableId":11,"textureId":11,"price":0,"label":null,"restrictionTags":null},{"componentId":5,"drawableId":11,"textureId":12,"price":0,"label":null,"restrictionTags":null},{"componentId":5,"drawableId":11,"textureId":13,"price":0,"label":null,"restrictionTags":null},{"componentId":5,"drawableId":11,"textureId":14,"price":0,"label":null,"restrictionTags":null},{"componentId":5,"drawableId":11,"textureId":15,"price":0,"label":null,"restrictionTags":null},{"componentId":5,"drawableId":11,"textureId":16,"price":0,"label":null,"restrictionTags":null},{"componentId":5,"drawableId":11,"textureId":17,"price":0,"label":null,"restrictionTags":null},{"componentId":5,"drawableId":11,"textureId":18,"price":0,"label":null,"restrictionTags":null},{"componentId":5,"drawableId":11,"textureId":19,"price":0,"label":null,"restrictionTags":null},{"componentId":5,"drawableId":11,"textureId":20,"price":0,"label":null,"restrictionTags":null},{"componentId":5,"drawableId":11,"textureId":21,"price":0,"label":null,"restrictionTags":null},{"componentId":5,"drawableId":11,"textureId":22,"price":0,"label":null,"restrictionTags":null},{"componentId":5,"drawableId":11,"textureId":23,"price":0,"label":null,"restrictionTags":null},{"componentId":5,"drawableId":11,"textureId":24,"price":0,"label":null,"restrictionTags":null},{"componentId":5,"drawableId":11,"textureId":25,"price":0,"label":null,"restrictionTags":null},{"componentId":5,"drawableId":12,"textureId":0,"price":0,"label":null,"restrictionTags":null},{"componentId":5,"drawableId":12,"textureId":1,"price":0,"label":null,"restrictionTags":null},{"componentId":5,"drawableId":12,"textureId":2,"price":0,"label":null,"restrictionTags":null},{"componentId":5,"drawableId":12,"textureId":3,"price":0,"label":null,"restrictionTags":null},{"componentId":5,"drawableId":12,"textureId":4,"price":0,"label":null,"restrictionTags":null},{"componentId":5,"drawableId":12,"textureId":5,"price":0,"label":null,"restrictionTags":null},{"componentId":5,"drawableId":12,"textureId":6,"price":0,"label":null,"restrictionTags":null},{"componentId":5,"drawableId":12,"textureId":7,"price":0,"label":null,"restrictionTags":null},{"componentId":5,"drawableId":12,"textureId":8,"price":0,"label":null,"restrictionTags":null},{"componentId":5,"drawableId":12,"textureId":9,"price":0,"label":null,"restrictionTags":null},{"componentId":5,"drawableId":12,"textureId":10,"price":0,"label":null,"restrictionTags":null},{"componentId":5,"drawableId":12,"textureId":11,"price":0,"label":null,"restrictionTags":null},{"componentId":5,"drawableId":12,"textureId":12,"price":0,"label":null,"restrictionTags":null},{"componentId":5,"drawableId":12,"textureId":13,"price":0,"label":null,"restrictionTags":null},{"componentId":5,"drawableId":12,"textureId":14,"price":0,"label":null,"restrictionTags":null},{"componentId":5,"drawableId":12,"textureId":15,"price":0,"label":null,"restrictionTags":null},{"componentId":5,"drawableId":12,"textureId":16,"price":0,"label":null,"restrictionTags":null},{"componentId":5,"drawableId":12,"textureId":17,"price":0,"label":null,"restrictionTags":null},{"componentId":5,"drawableId":12,"textureId":18,"price":0,"label":null,"restrictionTags":null},{"componentId":5,"drawableId":12,"textureId":19,"price":0,"label":null,"restrictionTags":null},{"componentId":5,"drawableId":12,"textureId":20,"price":0,"label":null,"restrictionTags":null},{"componentId":5,"drawableId":12,"textureId":21,"price":0,"label":null,"restrictionTags":null},{"componentId":5,"drawableId":12,"textureId":22,"price":0,"label":null,"restrictionTags":null},{"componentId":5,"drawableId":12,"textureId":23,"price":0,"label":null,"restrictionTags":null},{"componentId":5,"drawableId":12,"textureId":24,"price":0,"label":null,"restrictionTags":null},{"componentId":5,"drawableId":12,"textureId":25,"price":0,"label":null,"restrictionTags":null},{"componentId":5,"drawableId":13,"textureId":0,"price":0,"label":null,"restrictionTags":null},{"componentId":5,"drawableId":13,"textureId":1,"price":0,"label":null,"restrictionTags":null},{"componentId":5,"drawableId":13,"textureId":2,"price":0,"label":null,"restrictionTags":null},{"componentId":5,"drawableId":13,"textureId":3,"price":0,"label":null,"restrictionTags":null},{"componentId":5,"drawableId":13,"textureId":4,"price":0,"label":null,"restrictionTags":null},{"componentId":5,"drawableId":13,"textureId":5,"price":0,"label":null,"restrictionTags":null},{"componentId":5,"drawableId":13,"textureId":6,"price":0,"label":null,"restrictionTags":null},{"componentId":5,"drawableId":13,"textureId":7,"price":0,"label":null,"restrictionTags":null},{"componentId":5,"drawableId":13,"textureId":8,"price":0,"label":null,"restrictionTags":null},{"componentId":5,"drawableId":13,"textureId":9,"price":0,"label":null,"restrictionTags":null},{"componentId":5,"drawableId":13,"textureId":10,"price":0,"label":null,"restrictionTags":null},{"componentId":5,"drawableId":13,"textureId":11,"price":0,"label":null,"restrictionTags":null},{"componentId":5,"drawableId":13,"textureId":12,"price":0,"label":null,"restrictionTags":null},{"componentId":5,"drawableId":13,"textureId":13,"price":0,"label":null,"restrictionTags":null},{"componentId":5,"drawableId":13,"textureId":14,"price":0,"label":null,"restrictionTags":null},{"componentId":5,"drawableId":13,"textureId":15,"price":0,"label":null,"restrictionTags":null},{"componentId":5,"drawableId":13,"textureId":16,"price":0,"label":null,"restrictionTags":null},{"componentId":5,"drawableId":13,"textureId":17,"price":0,"label":null,"restrictionTags":null},{"componentId":5,"drawableId":13,"textureId":18,"price":0,"label":null,"restrictionTags":null},{"componentId":5,"drawableId":13,"textureId":19,"price":0,"label":null,"restrictionTags":null},{"componentId":5,"drawableId":13,"textureId":20,"price":0,"label":null,"restrictionTags":null},{"componentId":5,"drawableId":13,"textureId":21,"price":0,"label":null,"restrictionTags":null},{"componentId":5,"drawableId":13,"textureId":22,"price":0,"label":null,"restrictionTags":null},{"componentId":5,"drawableId":13,"textureId":23,"price":0,"label":null,"restrictionTags":null},{"componentId":5,"drawableId":13,"textureId":24,"price":0,"label":null,"restrictionTags":null},{"componentId":5,"drawableId":13,"textureId":25,"price":0,"label":null,"restrictionTags":null},{"componentId":5,"drawableId":14,"textureId":0,"price":0,"label":null,"restrictionTags":null},{"componentId":5,"drawableId":14,"textureId":1,"price":0,"label":null,"restrictionTags":null},{"componentId":5,"drawableId":14,"textureId":2,"price":0,"label":null,"restrictionTags":null},{"componentId":5,"drawableId":14,"textureId":3,"price":0,"label":null,"restrictionTags":null},{"componentId":5,"drawableId":14,"textureId":4,"price":0,"label":null,"restrictionTags":null},{"componentId":5,"drawableId":14,"textureId":5,"price":0,"label":null,"restrictionTags":null},{"componentId":5,"drawableId":14,"textureId":6,"price":0,"label":null,"restrictionTags":null},{"componentId":5,"drawableId":14,"textureId":7,"price":0,"label":null,"restrictionTags":null},{"componentId":5,"drawableId":14,"textureId":8,"price":0,"label":null,"restrictionTags":null},{"componentId":5,"drawableId":14,"textureId":9,"price":0,"label":null,"restrictionTags":null},{"componentId":5,"drawableId":14,"textureId":10,"price":0,"label":null,"restrictionTags":null},{"componentId":5,"drawableId":14,"textureId":11,"price":0,"label":null,"restrictionTags":null},{"componentId":5,"drawableId":14,"textureId":12,"price":0,"label":null,"restrictionTags":null},{"componentId":5,"drawableId":14,"textureId":13,"price":0,"label":null,"restrictionTags":null},{"componentId":5,"drawableId":14,"textureId":14,"price":0,"label":null,"restrictionTags":null},{"componentId":5,"drawableId":14,"textureId":15,"price":0,"label":null,"restrictionTags":null},{"componentId":5,"drawableId":14,"textureId":16,"price":0,"label":null,"restrictionTags":null},{"componentId":5,"drawableId":14,"textureId":17,"price":0,"label":null,"restrictionTags":null},{"componentId":5,"drawableId":14,"textureId":18,"price":0,"label":null,"restrictionTags":null},{"componentId":5,"drawableId":14,"textureId":19,"price":0,"label":null,"restrictionTags":null},{"componentId":5,"drawableId":14,"textureId":20,"price":0,"label":null,"restrictionTags":null},{"componentId":5,"drawableId":14,"textureId":21,"price":0,"label":null,"restrictionTags":null},{"componentId":5,"drawableId":14,"textureId":22,"price":0,"label":null,"restrictionTags":null},{"componentId":5,"drawableId":14,"textureId":23,"price":0,"label":null,"restrictionTags":null},{"componentId":5,"drawableId":14,"textureId":24,"price":0,"label":null,"restrictionTags":null},{"componentId":5,"drawableId":14,"textureId":25,"price":0,"label":null,"restrictionTags":null},{"componentId":5,"drawableId":15,"textureId":0,"price":0,"label":null,"restrictionTags":null},{"componentId":5,"drawableId":15,"textureId":1,"price":0,"label":null,"restrictionTags":null},{"componentId":5,"drawableId":15,"textureId":2,"price":0,"label":null,"restrictionTags":null},{"componentId":5,"drawableId":15,"textureId":3,"price":0,"label":null,"restrictionTags":null},{"componentId":5,"drawableId":15,"textureId":4,"price":0,"label":null,"restrictionTags":null},{"componentId":5,"drawableId":15,"textureId":5,"price":0,"label":null,"restrictionTags":null},{"componentId":5,"drawableId":15,"textureId":6,"price":0,"label":null,"restrictionTags":null},{"componentId":5,"drawableId":15,"textureId":7,"price":0,"label":null,"restrictionTags":null},{"componentId":5,"drawableId":15,"textureId":8,"price":0,"label":null,"restrictionTags":null},{"componentId":5,"drawableId":15,"textureId":9,"price":0,"label":null,"restrictionTags":null},{"componentId":5,"drawableId":15,"textureId":10,"price":0,"label":null,"restrictionTags":null},{"componentId":5,"drawableId":15,"textureId":11,"price":0,"label":null,"restrictionTags":null},{"componentId":5,"drawableId":15,"textureId":12,"price":0,"label":null,"restrictionTags":null},{"componentId":5,"drawableId":15,"textureId":13,"price":0,"label":null,"restrictionTags":null},{"componentId":5,"drawableId":15,"textureId":14,"price":0,"label":null,"restrictionTags":null},{"componentId":5,"drawableId":15,"textureId":15,"price":0,"label":null,"restrictionTags":null},{"componentId":5,"drawableId":15,"textureId":16,"price":0,"label":null,"restrictionTags":null},{"componentId":5,"drawableId":15,"textureId":17,"price":0,"label":null,"restrictionTags":null},{"componentId":5,"drawableId":15,"textureId":18,"price":0,"label":null,"restrictionTags":null},{"componentId":5,"drawableId":15,"textureId":19,"price":0,"label":null,"restrictionTags":null},{"componentId":5,"drawableId":15,"textureId":20,"price":0,"label":null,"restrictionTags":null},{"componentId":5,"drawableId":15,"textureId":21,"price":0,"label":null,"restrictionTags":null},{"componentId":5,"drawableId":15,"textureId":22,"price":0,"label":null,"restrictionTags":null},{"componentId":5,"drawableId":15,"textureId":23,"price":0,"label":null,"restrictionTags":null},{"componentId":5,"drawableId":15,"textureId":24,"price":0,"label":null,"restrictionTags":null},{"componentId":5,"drawableId":15,"textureId":25,"price":0,"label":null,"restrictionTags":null},{"componentId":5,"drawableId":16,"textureId":0,"price":0,"label":null,"restrictionTags":null},{"componentId":5,"drawableId":16,"textureId":1,"price":0,"label":null,"restrictionTags":null},{"componentId":5,"drawableId":16,"textureId":2,"price":0,"label":null,"restrictionTags":null},{"componentId":5,"drawableId":16,"textureId":3,"price":0,"label":null,"restrictionTags":null},{"componentId":5,"drawableId":16,"textureId":4,"price":0,"label":null,"restrictionTags":null},{"componentId":5,"drawableId":16,"textureId":5,"price":0,"label":null,"restrictionTags":null},{"componentId":5,"drawableId":16,"textureId":6,"price":0,"label":null,"restrictionTags":null},{"componentId":5,"drawableId":16,"textureId":7,"price":0,"label":null,"restrictionTags":null},{"componentId":5,"drawableId":16,"textureId":8,"price":0,"label":null,"restrictionTags":null},{"componentId":5,"drawableId":16,"textureId":9,"price":0,"label":null,"restrictionTags":null},{"componentId":5,"drawableId":16,"textureId":10,"price":0,"label":null,"restrictionTags":null},{"componentId":5,"drawableId":16,"textureId":11,"price":0,"label":null,"restrictionTags":null},{"componentId":5,"drawableId":16,"textureId":12,"price":0,"label":null,"restrictionTags":null},{"componentId":5,"drawableId":16,"textureId":13,"price":0,"label":null,"restrictionTags":null},{"componentId":5,"drawableId":16,"textureId":14,"price":0,"label":null,"restrictionTags":null},{"componentId":5,"drawableId":16,"textureId":15,"price":0,"label":null,"restrictionTags":null},{"componentId":5,"drawableId":16,"textureId":16,"price":0,"label":null,"restrictionTags":null},{"componentId":5,"drawableId":16,"textureId":17,"price":0,"label":null,"restrictionTags":null},{"componentId":5,"drawableId":16,"textureId":18,"price":0,"label":null,"restrictionTags":null},{"componentId":5,"drawableId":16,"textureId":19,"price":0,"label":null,"restrictionTags":null},{"componentId":5,"drawableId":16,"textureId":20,"price":0,"label":null,"restrictionTags":null},{"componentId":5,"drawableId":16,"textureId":21,"price":0,"label":null,"restrictionTags":null},{"componentId":5,"drawableId":16,"textureId":22,"price":0,"label":null,"restrictionTags":null},{"componentId":5,"drawableId":16,"textureId":23,"price":0,"label":null,"restrictionTags":null},{"componentId":5,"drawableId":16,"textureId":24,"price":0,"label":null,"restrictionTags":null},{"componentId":5,"drawableId":16,"textureId":25,"price":0,"label":null,"restrictionTags":null},{"componentId":5,"drawableId":17,"textureId":0,"price":0,"label":null,"restrictionTags":null},{"componentId":5,"drawableId":17,"textureId":1,"price":0,"label":null,"restrictionTags":null},{"componentId":5,"drawableId":17,"textureId":2,"price":0,"label":null,"restrictionTags":null},{"componentId":5,"drawableId":17,"textureId":3,"price":0,"label":null,"restrictionTags":null},{"componentId":5,"drawableId":17,"textureId":4,"price":0,"label":null,"restrictionTags":null},{"componentId":5,"drawableId":17,"textureId":5,"price":0,"label":null,"restrictionTags":null},{"componentId":5,"drawableId":17,"textureId":6,"price":0,"label":null,"restrictionTags":null},{"componentId":5,"drawableId":17,"textureId":7,"price":0,"label":null,"restrictionTags":null},{"componentId":5,"drawableId":17,"textureId":8,"price":0,"label":null,"restrictionTags":null},{"componentId":5,"drawableId":17,"textureId":9,"price":0,"label":null,"restrictionTags":null},{"componentId":5,"drawableId":17,"textureId":10,"price":0,"label":null,"restrictionTags":null},{"componentId":5,"drawableId":17,"textureId":11,"price":0,"label":null,"restrictionTags":null},{"componentId":5,"drawableId":17,"textureId":12,"price":0,"label":null,"restrictionTags":null},{"componentId":5,"drawableId":17,"textureId":13,"price":0,"label":null,"restrictionTags":null},{"componentId":5,"drawableId":17,"textureId":14,"price":0,"label":null,"restrictionTags":null},{"componentId":5,"drawableId":17,"textureId":15,"price":0,"label":null,"restrictionTags":null},{"componentId":5,"drawableId":17,"textureId":16,"price":0,"label":null,"restrictionTags":null},{"componentId":5,"drawableId":17,"textureId":17,"price":0,"label":null,"restrictionTags":null},{"componentId":5,"drawableId":17,"textureId":18,"price":0,"label":null,"restrictionTags":null},{"componentId":5,"drawableId":17,"textureId":19,"price":0,"label":null,"restrictionTags":null},{"componentId":5,"drawableId":17,"textureId":20,"price":0,"label":null,"restrictionTags":null},{"componentId":5,"drawableId":17,"textureId":21,"price":0,"label":null,"restrictionTags":null},{"componentId":5,"drawableId":17,"textureId":22,"price":0,"label":null,"restrictionTags":null},{"componentId":5,"drawableId":17,"textureId":23,"price":0,"label":null,"restrictionTags":null},{"componentId":5,"drawableId":17,"textureId":24,"price":0,"label":null,"restrictionTags":null},{"componentId":5,"drawableId":17,"textureId":25,"price":0,"label":null,"restrictionTags":null},{"componentId":5,"drawableId":18,"textureId":0,"price":0,"label":null,"restrictionTags":null},{"componentId":5,"drawableId":18,"textureId":1,"price":0,"label":null,"restrictionTags":null},{"componentId":5,"drawableId":18,"textureId":2,"price":0,"label":null,"restrictionTags":null},{"componentId":5,"drawableId":18,"textureId":3,"price":0,"label":null,"restrictionTags":null},{"componentId":5,"drawableId":18,"textureId":4,"price":0,"label":null,"restrictionTags":null},{"componentId":5,"drawableId":18,"textureId":5,"price":0,"label":null,"restrictionTags":null},{"componentId":5,"drawableId":18,"textureId":6,"price":0,"label":null,"restrictionTags":null},{"componentId":5,"drawableId":18,"textureId":7,"price":0,"label":null,"restrictionTags":null},{"componentId":5,"drawableId":18,"textureId":8,"price":0,"label":null,"restrictionTags":null},{"componentId":5,"drawableId":18,"textureId":9,"price":0,"label":null,"restrictionTags":null},{"componentId":5,"drawableId":18,"textureId":10,"price":0,"label":null,"restrictionTags":null},{"componentId":5,"drawableId":18,"textureId":11,"price":0,"label":null,"restrictionTags":null},{"componentId":5,"drawableId":18,"textureId":12,"price":0,"label":null,"restrictionTags":null},{"componentId":5,"drawableId":18,"textureId":13,"price":0,"label":null,"restrictionTags":null},{"componentId":5,"drawableId":18,"textureId":14,"price":0,"label":null,"restrictionTags":null},{"componentId":5,"drawableId":18,"textureId":15,"price":0,"label":null,"restrictionTags":null},{"componentId":5,"drawableId":18,"textureId":16,"price":0,"label":null,"restrictionTags":null},{"componentId":5,"drawableId":18,"textureId":17,"price":0,"label":null,"restrictionTags":null},{"componentId":5,"drawableId":18,"textureId":18,"price":0,"label":null,"restrictionTags":null},{"componentId":5,"drawableId":18,"textureId":19,"price":0,"label":null,"restrictionTags":null},{"componentId":5,"drawableId":18,"textureId":20,"price":0,"label":null,"restrictionTags":null},{"componentId":5,"drawableId":18,"textureId":21,"price":0,"label":null,"restrictionTags":null},{"componentId":5,"drawableId":18,"textureId":22,"price":0,"label":null,"restrictionTags":null},{"componentId":5,"drawableId":18,"textureId":23,"price":0,"label":null,"restrictionTags":null},{"componentId":5,"drawableId":18,"textureId":24,"price":0,"label":null,"restrictionTags":null},{"componentId":5,"drawableId":18,"textureId":25,"price":0,"label":null,"restrictionTags":null},{"componentId":5,"drawableId":19,"textureId":0,"price":0,"label":null,"restrictionTags":null},{"componentId":5,"drawableId":19,"textureId":1,"price":0,"label":null,"restrictionTags":null},{"componentId":5,"drawableId":19,"textureId":2,"price":0,"label":null,"restrictionTags":null},{"componentId":5,"drawableId":19,"textureId":3,"price":0,"label":null,"restrictionTags":null},{"componentId":5,"drawableId":19,"textureId":4,"price":0,"label":null,"restrictionTags":null},{"componentId":5,"drawableId":19,"textureId":5,"price":0,"label":null,"restrictionTags":null},{"componentId":5,"drawableId":19,"textureId":6,"price":0,"label":null,"restrictionTags":null},{"componentId":5,"drawableId":19,"textureId":7,"price":0,"label":null,"restrictionTags":null},{"componentId":5,"drawableId":19,"textureId":8,"price":0,"label":null,"restrictionTags":null},{"componentId":5,"drawableId":19,"textureId":9,"price":0,"label":null,"restrictionTags":null},{"componentId":5,"drawableId":19,"textureId":10,"price":0,"label":null,"restrictionTags":null},{"componentId":5,"drawableId":19,"textureId":11,"price":0,"label":null,"restrictionTags":null},{"componentId":5,"drawableId":19,"textureId":12,"price":0,"label":null,"restrictionTags":null},{"componentId":5,"drawableId":19,"textureId":13,"price":0,"label":null,"restrictionTags":null},{"componentId":5,"drawableId":19,"textureId":14,"price":0,"label":null,"restrictionTags":null},{"componentId":5,"drawableId":19,"textureId":15,"price":0,"label":null,"restrictionTags":null},{"componentId":5,"drawableId":19,"textureId":16,"price":0,"label":null,"restrictionTags":null},{"componentId":5,"drawableId":19,"textureId":17,"price":0,"label":null,"restrictionTags":null},{"componentId":5,"drawableId":19,"textureId":18,"price":0,"label":null,"restrictionTags":null},{"componentId":5,"drawableId":19,"textureId":19,"price":0,"label":null,"restrictionTags":null},{"componentId":5,"drawableId":19,"textureId":20,"price":0,"label":null,"restrictionTags":null},{"componentId":5,"drawableId":19,"textureId":21,"price":0,"label":null,"restrictionTags":null},{"componentId":5,"drawableId":19,"textureId":22,"price":0,"label":null,"restrictionTags":null},{"componentId":5,"drawableId":19,"textureId":23,"price":0,"label":null,"restrictionTags":null},{"componentId":5,"drawableId":19,"textureId":24,"price":0,"label":null,"restrictionTags":null},{"componentId":5,"drawableId":19,"textureId":25,"price":0,"label":null,"restrictionTags":null},{"componentId":5,"drawableId":20,"textureId":0,"price":0,"label":null,"restrictionTags":null},{"componentId":5,"drawableId":21,"textureId":0,"price":0,"label":null,"restrictionTags":null},{"componentId":5,"drawableId":22,"textureId":0,"price":0,"label":null,"restrictionTags":null},{"componentId":5,"drawableId":22,"textureId":1,"price":0,"label":null,"restrictionTags":null},{"componentId":5,"drawableId":22,"textureId":2,"price":0,"label":null,"restrictionTags":null},{"componentId":5,"drawableId":22,"textureId":3,"price":0,"label":null,"restrictionTags":null},{"componentId":5,"drawableId":22,"textureId":4,"price":0,"label":null,"restrictionTags":null},{"componentId":5,"drawableId":22,"textureId":5,"price":0,"label":null,"restrictionTags":null},{"componentId":5,"drawableId":22,"textureId":6,"price":0,"label":null,"restrictionTags":null},{"componentId":5,"drawableId":22,"textureId":7,"price":0,"label":null,"restrictionTags":null},{"componentId":5,"drawableId":22,"textureId":8,"price":0,"label":null,"restrictionTags":null},{"componentId":5,"drawableId":22,"textureId":9,"price":0,"label":null,"restrictionTags":null},{"componentId":5,"drawableId":22,"textureId":10,"price":0,"label":null,"restrictionTags":null},{"componentId":5,"drawableId":22,"textureId":11,"price":0,"label":null,"restrictionTags":null},{"componentId":5,"drawableId":22,"textureId":12,"price":0,"label":null,"restrictionTags":null},{"componentId":5,"drawableId":22,"textureId":13,"price":0,"label":null,"restrictionTags":null},{"componentId":5,"drawableId":22,"textureId":14,"price":0,"label":null,"restrictionTags":null},{"componentId":5,"drawableId":22,"textureId":15,"price":0,"label":null,"restrictionTags":null},{"componentId":5,"drawableId":22,"textureId":16,"price":0,"label":null,"restrictionTags":null},{"componentId":5,"drawableId":22,"textureId":17,"price":0,"label":null,"restrictionTags":null},{"componentId":5,"drawableId":22,"textureId":18,"price":0,"label":null,"restrictionTags":null},{"componentId":5,"drawableId":22,"textureId":19,"price":0,"label":null,"restrictionTags":null},{"componentId":5,"drawableId":22,"textureId":20,"price":0,"label":null,"restrictionTags":null},{"componentId":5,"drawableId":22,"textureId":21,"price":0,"label":null,"restrictionTags":null},{"componentId":5,"drawableId":22,"textureId":22,"price":0,"label":null,"restrictionTags":null},{"componentId":5,"drawableId":22,"textureId":23,"price":0,"label":null,"restrictionTags":null},{"componentId":5,"drawableId":22,"textureId":24,"price":0,"label":null,"restrictionTags":null},{"componentId":5,"drawableId":22,"textureId":25,"price":0,"label":null,"restrictionTags":null},{"componentId":5,"drawableId":23,"textureId":0,"price":0,"label":null,"restrictionTags":null},{"componentId":5,"drawableId":23,"textureId":1,"price":0,"label":null,"restrictionTags":null},{"componentId":5,"drawableId":23,"textureId":2,"price":0,"label":null,"restrictionTags":null},{"componentId":5,"drawableId":23,"textureId":3,"price":0,"label":null,"restrictionTags":null},{"componentId":5,"drawableId":23,"textureId":4,"price":0,"label":null,"restrictionTags":null},{"componentId":5,"drawableId":23,"textureId":5,"price":0,"label":null,"restrictionTags":null},{"componentId":5,"drawableId":23,"textureId":6,"price":0,"label":null,"restrictionTags":null},{"componentId":5,"drawableId":23,"textureId":7,"price":0,"label":null,"restrictionTags":null},{"componentId":5,"drawableId":23,"textureId":8,"price":0,"label":null,"restrictionTags":null},{"componentId":5,"drawableId":23,"textureId":9,"price":0,"label":null,"restrictionTags":null},{"componentId":5,"drawableId":23,"textureId":10,"price":0,"label":null,"restrictionTags":null},{"componentId":5,"drawableId":23,"textureId":11,"price":0,"label":null,"restrictionTags":null},{"componentId":5,"drawableId":23,"textureId":12,"price":0,"label":null,"restrictionTags":null},{"componentId":5,"drawableId":23,"textureId":13,"price":0,"label":null,"restrictionTags":null},{"componentId":5,"drawableId":23,"textureId":14,"price":0,"label":null,"restrictionTags":null},{"componentId":5,"drawableId":23,"textureId":15,"price":0,"label":null,"restrictionTags":null},{"componentId":5,"drawableId":23,"textureId":16,"price":0,"label":null,"restrictionTags":null},{"componentId":5,"drawableId":23,"textureId":17,"price":0,"label":null,"restrictionTags":null},{"componentId":5,"drawableId":23,"textureId":18,"price":0,"label":null,"restrictionTags":null},{"componentId":5,"drawableId":23,"textureId":19,"price":0,"label":null,"restrictionTags":null},{"componentId":5,"drawableId":23,"textureId":20,"price":0,"label":null,"restrictionTags":null},{"componentId":5,"drawableId":23,"textureId":21,"price":0,"label":null,"restrictionTags":null},{"componentId":5,"drawableId":23,"textureId":22,"price":0,"label":null,"restrictionTags":null},{"componentId":5,"drawableId":23,"textureId":23,"price":0,"label":null,"restrictionTags":null},{"componentId":5,"drawableId":23,"textureId":24,"price":0,"label":null,"restrictionTags":null},{"componentId":5,"drawableId":23,"textureId":25,"price":0,"label":null,"restrictionTags":null},{"componentId":5,"drawableId":24,"textureId":0,"price":0,"label":null,"restrictionTags":null},{"componentId":5,"drawableId":24,"textureId":1,"price":0,"label":null,"restrictionTags":null},{"componentId":5,"drawableId":24,"textureId":2,"price":0,"label":null,"restrictionTags":null},{"componentId":5,"drawableId":24,"textureId":3,"price":0,"label":null,"restrictionTags":null},{"componentId":5,"drawableId":24,"textureId":4,"price":0,"label":null,"restrictionTags":null},{"componentId":5,"drawableId":24,"textureId":5,"price":0,"label":null,"restrictionTags":null},{"componentId":5,"drawableId":24,"textureId":6,"price":0,"label":null,"restrictionTags":null},{"componentId":5,"drawableId":24,"textureId":7,"price":0,"label":null,"restrictionTags":null},{"componentId":5,"drawableId":24,"textureId":8,"price":0,"label":null,"restrictionTags":null},{"componentId":5,"drawableId":24,"textureId":9,"price":0,"label":null,"restrictionTags":null},{"componentId":5,"drawableId":24,"textureId":10,"price":0,"label":null,"restrictionTags":null},{"componentId":5,"drawableId":24,"textureId":11,"price":0,"label":null,"restrictionTags":null},{"componentId":5,"drawableId":24,"textureId":12,"price":0,"label":null,"restrictionTags":null},{"componentId":5,"drawableId":24,"textureId":13,"price":0,"label":null,"restrictionTags":null},{"componentId":5,"drawableId":24,"textureId":14,"price":0,"label":null,"restrictionTags":null},{"componentId":5,"drawableId":24,"textureId":15,"price":0,"label":null,"restrictionTags":null},{"componentId":5,"drawableId":24,"textureId":16,"price":0,"label":null,"restrictionTags":null},{"componentId":5,"drawableId":24,"textureId":17,"price":0,"label":null,"restrictionTags":null},{"componentId":5,"drawableId":24,"textureId":18,"price":0,"label":null,"restrictionTags":null},{"componentId":5,"drawableId":24,"textureId":19,"price":0,"label":null,"restrictionTags":null},{"componentId":5,"drawableId":24,"textureId":20,"price":0,"label":null,"restrictionTags":null},{"componentId":5,"drawableId":24,"textureId":21,"price":0,"label":null,"restrictionTags":null},{"componentId":5,"drawableId":24,"textureId":22,"price":0,"label":null,"restrictionTags":null},{"componentId":5,"drawableId":24,"textureId":23,"price":0,"label":null,"restrictionTags":null},{"componentId":5,"drawableId":24,"textureId":24,"price":0,"label":null,"restrictionTags":null},{"componentId":5,"drawableId":24,"textureId":25,"price":0,"label":null,"restrictionTags":null},{"componentId":5,"drawableId":25,"textureId":0,"price":0,"label":null,"restrictionTags":null},{"componentId":5,"drawableId":25,"textureId":1,"price":0,"label":null,"restrictionTags":null},{"componentId":5,"drawableId":25,"textureId":2,"price":0,"label":null,"restrictionTags":null},{"componentId":5,"drawableId":25,"textureId":3,"price":0,"label":null,"restrictionTags":null},{"componentId":5,"drawableId":25,"textureId":4,"price":0,"label":null,"restrictionTags":null},{"componentId":5,"drawableId":25,"textureId":5,"price":0,"label":null,"restrictionTags":null},{"componentId":5,"drawableId":25,"textureId":6,"price":0,"label":null,"restrictionTags":null},{"componentId":5,"drawableId":25,"textureId":7,"price":0,"label":null,"restrictionTags":null},{"componentId":5,"drawableId":25,"textureId":8,"price":0,"label":null,"restrictionTags":null},{"componentId":5,"drawableId":25,"textureId":9,"price":0,"label":null,"restrictionTags":null},{"componentId":5,"drawableId":25,"textureId":10,"price":0,"label":null,"restrictionTags":null},{"componentId":5,"drawableId":25,"textureId":11,"price":0,"label":null,"restrictionTags":null},{"componentId":5,"drawableId":25,"textureId":12,"price":0,"label":null,"restrictionTags":null},{"componentId":5,"drawableId":25,"textureId":13,"price":0,"label":null,"restrictionTags":null},{"componentId":5,"drawableId":25,"textureId":14,"price":0,"label":null,"restrictionTags":null},{"componentId":5,"drawableId":25,"textureId":15,"price":0,"label":null,"restrictionTags":null},{"componentId":5,"drawableId":25,"textureId":16,"price":0,"label":null,"restrictionTags":null},{"componentId":5,"drawableId":25,"textureId":17,"price":0,"label":null,"restrictionTags":null},{"componentId":5,"drawableId":25,"textureId":18,"price":0,"label":null,"restrictionTags":null},{"componentId":5,"drawableId":25,"textureId":19,"price":0,"label":null,"restrictionTags":null},{"componentId":5,"drawableId":25,"textureId":20,"price":0,"label":null,"restrictionTags":null},{"componentId":5,"drawableId":25,"textureId":21,"price":0,"label":null,"restrictionTags":null},{"componentId":5,"drawableId":25,"textureId":22,"price":0,"label":null,"restrictionTags":null},{"componentId":5,"drawableId":25,"textureId":23,"price":0,"label":null,"restrictionTags":null},{"componentId":5,"drawableId":25,"textureId":24,"price":0,"label":null,"restrictionTags":null},{"componentId":5,"drawableId":25,"textureId":25,"price":0,"label":null,"restrictionTags":null},{"componentId":5,"drawableId":26,"textureId":0,"price":0,"label":null,"restrictionTags":null},{"componentId":5,"drawableId":26,"textureId":1,"price":0,"label":null,"restrictionTags":null},{"componentId":5,"drawableId":26,"textureId":2,"price":0,"label":null,"restrictionTags":null},{"componentId":5,"drawableId":26,"textureId":3,"price":0,"label":null,"restrictionTags":null},{"componentId":5,"drawableId":26,"textureId":4,"price":0,"label":null,"restrictionTags":null},{"componentId":5,"drawableId":26,"textureId":5,"price":0,"label":null,"restrictionTags":null},{"componentId":5,"drawableId":26,"textureId":6,"price":0,"label":null,"restrictionTags":null},{"componentId":5,"drawableId":26,"textureId":7,"price":0,"label":null,"restrictionTags":null},{"componentId":5,"drawableId":26,"textureId":8,"price":0,"label":null,"restrictionTags":null},{"componentId":5,"drawableId":26,"textureId":9,"price":0,"label":null,"restrictionTags":null},{"componentId":5,"drawableId":26,"textureId":10,"price":0,"label":null,"restrictionTags":null},{"componentId":5,"drawableId":26,"textureId":11,"price":0,"label":null,"restrictionTags":null},{"componentId":5,"drawableId":26,"textureId":12,"price":0,"label":null,"restrictionTags":null},{"componentId":5,"drawableId":26,"textureId":13,"price":0,"label":null,"restrictionTags":null},{"componentId":5,"drawableId":26,"textureId":14,"price":0,"label":null,"restrictionTags":null},{"componentId":5,"drawableId":26,"textureId":15,"price":0,"label":null,"restrictionTags":null},{"componentId":5,"drawableId":26,"textureId":16,"price":0,"label":null,"restrictionTags":null},{"componentId":5,"drawableId":26,"textureId":17,"price":0,"label":null,"restrictionTags":null},{"componentId":5,"drawableId":26,"textureId":18,"price":0,"label":null,"restrictionTags":null},{"componentId":5,"drawableId":26,"textureId":19,"price":0,"label":null,"restrictionTags":null},{"componentId":5,"drawableId":26,"textureId":20,"price":0,"label":null,"restrictionTags":null},{"componentId":5,"drawableId":26,"textureId":21,"price":0,"label":null,"restrictionTags":null},{"componentId":5,"drawableId":26,"textureId":22,"price":0,"label":null,"restrictionTags":null},{"componentId":5,"drawableId":26,"textureId":23,"price":0,"label":null,"restrictionTags":null},{"componentId":5,"drawableId":26,"textureId":24,"price":0,"label":null,"restrictionTags":null},{"componentId":5,"drawableId":26,"textureId":25,"price":0,"label":null,"restrictionTags":null},{"componentId":5,"drawableId":27,"textureId":0,"price":0,"label":null,"restrictionTags":null},{"componentId":5,"drawableId":27,"textureId":1,"price":0,"label":null,"restrictionTags":null},{"componentId":5,"drawableId":27,"textureId":2,"price":0,"label":null,"restrictionTags":null},{"componentId":5,"drawableId":27,"textureId":3,"price":0,"label":null,"restrictionTags":null},{"componentId":5,"drawableId":27,"textureId":4,"price":0,"label":null,"restrictionTags":null},{"componentId":5,"drawableId":27,"textureId":5,"price":0,"label":null,"restrictionTags":null},{"componentId":5,"drawableId":27,"textureId":6,"price":0,"label":null,"restrictionTags":null},{"componentId":5,"drawableId":27,"textureId":7,"price":0,"label":null,"restrictionTags":null},{"componentId":5,"drawableId":27,"textureId":8,"price":0,"label":null,"restrictionTags":null},{"componentId":5,"drawableId":27,"textureId":9,"price":0,"label":null,"restrictionTags":null},{"componentId":5,"drawableId":27,"textureId":10,"price":0,"label":null,"restrictionTags":null},{"componentId":5,"drawableId":27,"textureId":11,"price":0,"label":null,"restrictionTags":null},{"componentId":5,"drawableId":27,"textureId":12,"price":0,"label":null,"restrictionTags":null},{"componentId":5,"drawableId":27,"textureId":13,"price":0,"label":null,"restrictionTags":null},{"componentId":5,"drawableId":27,"textureId":14,"price":0,"label":null,"restrictionTags":null},{"componentId":5,"drawableId":27,"textureId":15,"price":0,"label":null,"restrictionTags":null},{"componentId":5,"drawableId":27,"textureId":16,"price":0,"label":null,"restrictionTags":null},{"componentId":5,"drawableId":27,"textureId":17,"price":0,"label":null,"restrictionTags":null},{"componentId":5,"drawableId":27,"textureId":18,"price":0,"label":null,"restrictionTags":null},{"componentId":5,"drawableId":27,"textureId":19,"price":0,"label":null,"restrictionTags":null},{"componentId":5,"drawableId":27,"textureId":20,"price":0,"label":null,"restrictionTags":null},{"componentId":5,"drawableId":27,"textureId":21,"price":0,"label":null,"restrictionTags":null},{"componentId":5,"drawableId":27,"textureId":22,"price":0,"label":null,"restrictionTags":null},{"componentId":5,"drawableId":27,"textureId":23,"price":0,"label":null,"restrictionTags":null},{"componentId":5,"drawableId":27,"textureId":24,"price":0,"label":null,"restrictionTags":null},{"componentId":5,"drawableId":27,"textureId":25,"price":0,"label":null,"restrictionTags":null},{"componentId":5,"drawableId":28,"textureId":0,"price":0,"label":null,"restrictionTags":null},{"componentId":5,"drawableId":28,"textureId":1,"price":0,"label":null,"restrictionTags":null},{"componentId":5,"drawableId":28,"textureId":2,"price":0,"label":null,"restrictionTags":null},{"componentId":5,"drawableId":28,"textureId":3,"price":0,"label":null,"restrictionTags":null},{"componentId":5,"drawableId":28,"textureId":4,"price":0,"label":null,"restrictionTags":null},{"componentId":5,"drawableId":28,"textureId":5,"price":0,"label":null,"restrictionTags":null},{"componentId":5,"drawableId":28,"textureId":6,"price":0,"label":null,"restrictionTags":null},{"componentId":5,"drawableId":28,"textureId":7,"price":0,"label":null,"restrictionTags":null},{"componentId":5,"drawableId":28,"textureId":8,"price":0,"label":null,"restrictionTags":null},{"componentId":5,"drawableId":28,"textureId":9,"price":0,"label":null,"restrictionTags":null},{"componentId":5,"drawableId":28,"textureId":10,"price":0,"label":null,"restrictionTags":null},{"componentId":5,"drawableId":28,"textureId":11,"price":0,"label":null,"restrictionTags":null},{"componentId":5,"drawableId":28,"textureId":12,"price":0,"label":null,"restrictionTags":null},{"componentId":5,"drawableId":28,"textureId":13,"price":0,"label":null,"restrictionTags":null},{"componentId":5,"drawableId":28,"textureId":14,"price":0,"label":null,"restrictionTags":null},{"componentId":5,"drawableId":28,"textureId":15,"price":0,"label":null,"restrictionTags":null},{"componentId":5,"drawableId":28,"textureId":16,"price":0,"label":null,"restrictionTags":null},{"componentId":5,"drawableId":28,"textureId":17,"price":0,"label":null,"restrictionTags":null},{"componentId":5,"drawableId":28,"textureId":18,"price":0,"label":null,"restrictionTags":null},{"componentId":5,"drawableId":28,"textureId":19,"price":0,"label":null,"restrictionTags":null},{"componentId":5,"drawableId":28,"textureId":20,"price":0,"label":null,"restrictionTags":null},{"componentId":5,"drawableId":28,"textureId":21,"price":0,"label":null,"restrictionTags":null},{"componentId":5,"drawableId":28,"textureId":22,"price":0,"label":null,"restrictionTags":null},{"componentId":5,"drawableId":28,"textureId":23,"price":0,"label":null,"restrictionTags":null},{"componentId":5,"drawableId":28,"textureId":24,"price":0,"label":null,"restrictionTags":null},{"componentId":5,"drawableId":28,"textureId":25,"price":0,"label":null,"restrictionTags":null},{"componentId":5,"drawableId":29,"textureId":0,"price":0,"label":null,"restrictionTags":null},{"componentId":5,"drawableId":29,"textureId":1,"price":0,"label":null,"restrictionTags":null},{"componentId":5,"drawableId":29,"textureId":2,"price":0,"label":null,"restrictionTags":null},{"componentId":5,"drawableId":29,"textureId":3,"price":0,"label":null,"restrictionTags":null},{"componentId":5,"drawableId":29,"textureId":4,"price":0,"label":null,"restrictionTags":null},{"componentId":5,"drawableId":29,"textureId":5,"price":0,"label":null,"restrictionTags":null},{"componentId":5,"drawableId":29,"textureId":6,"price":0,"label":null,"restrictionTags":null},{"componentId":5,"drawableId":29,"textureId":7,"price":0,"label":null,"restrictionTags":null},{"componentId":5,"drawableId":29,"textureId":8,"price":0,"label":null,"restrictionTags":null},{"componentId":5,"drawableId":29,"textureId":9,"price":0,"label":null,"restrictionTags":null},{"componentId":5,"drawableId":29,"textureId":10,"price":0,"label":null,"restrictionTags":null},{"componentId":5,"drawableId":29,"textureId":11,"price":0,"label":null,"restrictionTags":null},{"componentId":5,"drawableId":29,"textureId":12,"price":0,"label":null,"restrictionTags":null},{"componentId":5,"drawableId":29,"textureId":13,"price":0,"label":null,"restrictionTags":null},{"componentId":5,"drawableId":29,"textureId":14,"price":0,"label":null,"restrictionTags":null},{"componentId":5,"drawableId":29,"textureId":15,"price":0,"label":null,"restrictionTags":null},{"componentId":5,"drawableId":29,"textureId":16,"price":0,"label":null,"restrictionTags":null},{"componentId":5,"drawableId":29,"textureId":17,"price":0,"label":null,"restrictionTags":null},{"componentId":5,"drawableId":29,"textureId":18,"price":0,"label":null,"restrictionTags":null},{"componentId":5,"drawableId":29,"textureId":19,"price":0,"label":null,"restrictionTags":null},{"componentId":5,"drawableId":29,"textureId":20,"price":0,"label":null,"restrictionTags":null},{"componentId":5,"drawableId":29,"textureId":21,"price":0,"label":null,"restrictionTags":null},{"componentId":5,"drawableId":29,"textureId":22,"price":0,"label":null,"restrictionTags":null},{"componentId":5,"drawableId":29,"textureId":23,"price":0,"label":null,"restrictionTags":null},{"componentId":5,"drawableId":29,"textureId":24,"price":0,"label":null,"restrictionTags":null},{"componentId":5,"drawableId":29,"textureId":25,"price":0,"label":null,"restrictionTags":null},{"componentId":5,"drawableId":30,"textureId":0,"price":0,"label":null,"restrictionTags":null},{"componentId":5,"drawableId":30,"textureId":1,"price":0,"label":null,"restrictionTags":null},{"componentId":5,"drawableId":30,"textureId":2,"price":0,"label":null,"restrictionTags":null},{"componentId":5,"drawableId":30,"textureId":3,"price":0,"label":null,"restrictionTags":null},{"componentId":5,"drawableId":30,"textureId":4,"price":0,"label":null,"restrictionTags":null},{"componentId":5,"drawableId":30,"textureId":5,"price":0,"label":null,"restrictionTags":null},{"componentId":5,"drawableId":30,"textureId":6,"price":0,"label":null,"restrictionTags":null},{"componentId":5,"drawableId":30,"textureId":7,"price":0,"label":null,"restrictionTags":null},{"componentId":5,"drawableId":30,"textureId":8,"price":0,"label":null,"restrictionTags":null},{"componentId":5,"drawableId":30,"textureId":9,"price":0,"label":null,"restrictionTags":null},{"componentId":5,"drawableId":30,"textureId":10,"price":0,"label":null,"restrictionTags":null},{"componentId":5,"drawableId":30,"textureId":11,"price":0,"label":null,"restrictionTags":null},{"componentId":5,"drawableId":30,"textureId":12,"price":0,"label":null,"restrictionTags":null},{"componentId":5,"drawableId":30,"textureId":13,"price":0,"label":null,"restrictionTags":null},{"componentId":5,"drawableId":30,"textureId":14,"price":0,"label":null,"restrictionTags":null},{"componentId":5,"drawableId":30,"textureId":15,"price":0,"label":null,"restrictionTags":null},{"componentId":5,"drawableId":30,"textureId":16,"price":0,"label":null,"restrictionTags":null},{"componentId":5,"drawableId":30,"textureId":17,"price":0,"label":null,"restrictionTags":null},{"componentId":5,"drawableId":30,"textureId":18,"price":0,"label":null,"restrictionTags":null},{"componentId":5,"drawableId":30,"textureId":19,"price":0,"label":null,"restrictionTags":null},{"componentId":5,"drawableId":30,"textureId":20,"price":0,"label":null,"restrictionTags":null},{"componentId":5,"drawableId":30,"textureId":21,"price":0,"label":null,"restrictionTags":null},{"componentId":5,"drawableId":30,"textureId":22,"price":0,"label":null,"restrictionTags":null},{"componentId":5,"drawableId":30,"textureId":23,"price":0,"label":null,"restrictionTags":null},{"componentId":5,"drawableId":30,"textureId":24,"price":0,"label":null,"restrictionTags":null},{"componentId":5,"drawableId":30,"textureId":25,"price":0,"label":null,"restrictionTags":null},{"componentId":5,"drawableId":31,"textureId":0,"price":0,"label":null,"restrictionTags":["DUFFEL_BAG"]},{"componentId":5,"drawableId":32,"textureId":0,"price":0,"label":null,"restrictionTags":["DUFFEL_BAG"]},{"componentId":5,"drawableId":33,"textureId":0,"price":0,"label":null,"restrictionTags":["DUFFEL_BAG"]},{"componentId":5,"drawableId":34,"textureId":0,"price":0,"label":null,"restrictionTags":["DUFFEL_BAG"]},{"componentId":5,"drawableId":35,"textureId":0,"price":0,"label":null,"restrictionTags":["DUFFEL_BAG"]},{"componentId":5,"drawableId":36,"textureId":0,"price":0,"label":null,"restrictionTags":["DUFFEL_BAG"]},{"componentId":5,"drawableId":37,"textureId":0,"price":0,"label":null,"restrictionTags":["DUFFEL_BAG"]},{"componentId":5,"drawableId":38,"textureId":0,"price":0,"label":null,"restrictionTags":["DUFFEL_BAG"]},{"componentId":5,"drawableId":39,"textureId":0,"price":0,"label":null,"restrictionTags":["PARACHUTE"]},{"componentId":5,"drawableId":40,"textureId":0,"price":0,"label":null,"restrictionTags":["PARACHUTE"]},{"componentId":5,"drawableId":40,"textureId":1,"price":0,"label":null,"restrictionTags":["PARACHUTE"]},{"componentId":5,"drawableId":40,"textureId":2,"price":0,"label":null,"restrictionTags":["PARACHUTE"]},{"componentId":5,"drawableId":40,"textureId":3,"price":0,"label":null,"restrictionTags":["PARACHUTE"]},{"componentId":5,"drawableId":40,"textureId":4,"price":0,"label":null,"restrictionTags":["PARACHUTE"]},{"componentId":5,"drawableId":40,"textureId":5,"price":0,"label":null,"restrictionTags":["PARACHUTE"]},{"componentId":5,"drawableId":40,"textureId":6,"price":0,"label":null,"restrictionTags":["PARACHUTE"]},{"componentId":5,"drawableId":40,"textureId":7,"price":0,"label":null,"restrictionTags":["PARACHUTE"]},{"componentId":5,"drawableId":40,"textureId":8,"price":0,"label":null,"restrictionTags":["PARACHUTE"]},{"componentId":5,"drawableId":40,"textureId":9,"price":0,"label":null,"restrictionTags":["PARACHUTE"]},{"componentId":5,"drawableId":40,"textureId":10,"price":0,"label":null,"restrictionTags":["PARACHUTE"]},{"componentId":5,"drawableId":40,"textureId":11,"price":0,"label":null,"restrictionTags":["PARACHUTE"]},{"componentId":5,"drawableId":40,"textureId":12,"price":0,"label":null,"restrictionTags":["PARACHUTE"]},{"componentId":5,"drawableId":40,"textureId":13,"price":0,"label":null,"restrictionTags":["PARACHUTE"]},{"componentId":5,"drawableId":40,"textureId":14,"price":0,"label":null,"restrictionTags":["PARACHUTE"]},{"componentId":5,"drawableId":40,"textureId":15,"price":0,"label":null,"restrictionTags":["PARACHUTE"]},{"componentId":5,"drawableId":40,"textureId":16,"price":0,"label":null,"restrictionTags":["PARACHUTE"]},{"componentId":5,"drawableId":40,"textureId":17,"price":0,"label":null,"restrictionTags":["PARACHUTE"]},{"componentId":5,"drawableId":40,"textureId":18,"price":0,"label":null,"restrictionTags":["PARACHUTE"]},{"componentId":5,"drawableId":40,"textureId":19,"price":0,"label":null,"restrictionTags":["PARACHUTE"]},{"componentId":5,"drawableId":40,"textureId":20,"price":0,"label":null,"restrictionTags":["PARACHUTE"]},{"componentId":5,"drawableId":40,"textureId":21,"price":0,"label":null,"restrictionTags":["PARACHUTE"]},{"componentId":5,"drawableId":40,"textureId":22,"price":0,"label":null,"restrictionTags":["PARACHUTE"]},{"componentId":5,"drawableId":40,"textureId":23,"price":0,"label":null,"restrictionTags":["PARACHUTE"]},{"componentId":5,"drawableId":40,"textureId":24,"price":0,"label":null,"restrictionTags":["PARACHUTE"]},{"componentId":5,"drawableId":40,"textureId":25,"price":0,"label":null,"restrictionTags":["PARACHUTE"]},{"componentId":5,"drawableId":41,"textureId":0,"price":0,"label":null,"restrictionTags":["PARACHUTE"]},{"componentId":5,"drawableId":41,"textureId":1,"price":0,"label":null,"restrictionTags":["PARACHUTE"]},{"componentId":5,"drawableId":41,"textureId":2,"price":0,"label":null,"restrictionTags":["PARACHUTE"]},{"componentId":5,"drawableId":41,"textureId":3,"price":0,"label":null,"restrictionTags":["PARACHUTE"]},{"componentId":5,"drawableId":41,"textureId":4,"price":0,"label":null,"restrictionTags":["PARACHUTE"]},{"componentId":5,"drawableId":41,"textureId":5,"price":0,"label":null,"restrictionTags":["PARACHUTE"]},{"componentId":5,"drawableId":41,"textureId":6,"price":0,"label":null,"restrictionTags":["PARACHUTE"]},{"componentId":5,"drawableId":41,"textureId":7,"price":0,"label":null,"restrictionTags":["PARACHUTE"]},{"componentId":5,"drawableId":41,"textureId":8,"price":0,"label":null,"restrictionTags":["PARACHUTE"]},{"componentId":5,"drawableId":41,"textureId":9,"price":0,"label":null,"restrictionTags":["PARACHUTE"]},{"componentId":5,"drawableId":41,"textureId":10,"price":0,"label":null,"restrictionTags":["PARACHUTE"]},{"componentId":5,"drawableId":41,"textureId":11,"price":0,"label":null,"restrictionTags":["PARACHUTE"]},{"componentId":5,"drawableId":41,"textureId":12,"price":0,"label":null,"restrictionTags":["PARACHUTE"]},{"componentId":5,"drawableId":41,"textureId":13,"price":0,"label":null,"restrictionTags":["PARACHUTE"]},{"componentId":5,"drawableId":41,"textureId":14,"price":0,"label":null,"restrictionTags":["PARACHUTE"]},{"componentId":5,"drawableId":41,"textureId":15,"price":0,"label":null,"restrictionTags":["PARACHUTE"]},{"componentId":5,"drawableId":41,"textureId":16,"price":0,"label":null,"restrictionTags":["PARACHUTE"]},{"componentId":5,"drawableId":41,"textureId":17,"price":0,"label":null,"restrictionTags":["PARACHUTE"]},{"componentId":5,"drawableId":41,"textureId":18,"price":0,"label":null,"restrictionTags":["PARACHUTE"]},{"componentId":5,"drawableId":41,"textureId":19,"price":0,"label":null,"restrictionTags":["PARACHUTE"]},{"componentId":5,"drawableId":41,"textureId":20,"price":0,"label":null,"restrictionTags":["PARACHUTE"]},{"componentId":5,"drawableId":41,"textureId":21,"price":0,"label":null,"restrictionTags":["PARACHUTE"]},{"componentId":5,"drawableId":41,"textureId":22,"price":0,"label":null,"restrictionTags":["PARACHUTE"]},{"componentId":5,"drawableId":41,"textureId":23,"price":0,"label":null,"restrictionTags":["PARACHUTE"]},{"componentId":5,"drawableId":41,"textureId":24,"price":0,"label":null,"restrictionTags":["PARACHUTE"]},{"componentId":5,"drawableId":41,"textureId":25,"price":0,"label":null,"restrictionTags":["PARACHUTE"]},{"componentId":5,"drawableId":42,"textureId":0,"price":0,"label":null,"restrictionTags":["PARACHUTE"]},{"componentId":5,"drawableId":42,"textureId":1,"price":0,"label":null,"restrictionTags":["PARACHUTE"]},{"componentId":5,"drawableId":42,"textureId":2,"price":0,"label":null,"restrictionTags":["PARACHUTE"]},{"componentId":5,"drawableId":42,"textureId":3,"price":0,"label":null,"restrictionTags":["PARACHUTE"]},{"componentId":5,"drawableId":42,"textureId":4,"price":0,"label":null,"restrictionTags":["PARACHUTE"]},{"componentId":5,"drawableId":43,"textureId":0,"price":0,"label":null,"restrictionTags":["PARACHUTE"]},{"componentId":5,"drawableId":44,"textureId":0,"price":0,"label":null,"restrictionTags":["PARACHUTE"]},{"componentId":5,"drawableId":45,"textureId":0,"price":0,"label":null,"restrictionTags":["PARACHUTE"]},{"componentId":5,"drawableId":45,"textureId":1,"price":0,"label":null,"restrictionTags":["PARACHUTE"]},{"componentId":5,"drawableId":45,"textureId":2,"price":0,"label":null,"restrictionTags":["PARACHUTE"]},{"componentId":5,"drawableId":45,"textureId":3,"price":0,"label":null,"restrictionTags":["PARACHUTE"]},{"componentId":5,"drawableId":45,"textureId":4,"price":0,"label":null,"restrictionTags":["PARACHUTE"]},{"componentId":5,"drawableId":45,"textureId":5,"price":0,"label":null,"restrictionTags":["PARACHUTE"]},{"componentId":5,"drawableId":45,"textureId":6,"price":0,"label":null,"restrictionTags":["PARACHUTE"]},{"componentId":5,"drawableId":45,"textureId":7,"price":0,"label":null,"restrictionTags":["PARACHUTE"]},{"componentId":5,"drawableId":45,"textureId":8,"price":0,"label":null,"restrictionTags":["PARACHUTE"]},{"componentId":5,"drawableId":45,"textureId":9,"price":0,"label":null,"restrictionTags":["PARACHUTE"]},{"componentId":5,"drawableId":45,"textureId":10,"price":0,"label":null,"restrictionTags":["PARACHUTE"]},{"componentId":5,"drawableId":45,"textureId":11,"price":0,"label":null,"restrictionTags":["PARACHUTE"]},{"componentId":5,"drawableId":45,"textureId":12,"price":0,"label":null,"restrictionTags":["PARACHUTE"]},{"componentId":5,"drawableId":45,"textureId":13,"price":0,"label":null,"restrictionTags":["PARACHUTE"]},{"componentId":5,"drawableId":45,"textureId":14,"price":0,"label":null,"restrictionTags":["PARACHUTE"]},{"componentId":5,"drawableId":45,"textureId":15,"price":0,"label":null,"restrictionTags":["PARACHUTE"]},{"componentId":5,"drawableId":45,"textureId":16,"price":0,"label":null,"restrictionTags":["PARACHUTE"]},{"componentId":5,"drawableId":45,"textureId":17,"price":0,"label":null,"restrictionTags":["PARACHUTE"]},{"componentId":5,"drawableId":45,"textureId":18,"price":0,"label":null,"restrictionTags":["PARACHUTE"]},{"componentId":5,"drawableId":45,"textureId":19,"price":0,"label":null,"restrictionTags":["PARACHUTE"]},{"componentId":5,"drawableId":45,"textureId":20,"price":0,"label":null,"restrictionTags":["PARACHUTE"]},{"componentId":5,"drawableId":45,"textureId":21,"price":0,"label":null,"restrictionTags":["PARACHUTE"]},{"componentId":5,"drawableId":45,"textureId":22,"price":0,"label":null,"restrictionTags":["PARACHUTE"]},{"componentId":5,"drawableId":45,"textureId":23,"price":0,"label":null,"restrictionTags":["PARACHUTE"]},{"componentId":5,"drawableId":45,"textureId":24,"price":0,"label":null,"restrictionTags":["PARACHUTE"]},{"componentId":5,"drawableId":45,"textureId":25,"price":0,"label":null,"restrictionTags":["PARACHUTE"]},{"componentId":5,"drawableId":46,"textureId":0,"price":0,"label":null,"restrictionTags":["PARACHUTE"]},{"componentId":5,"drawableId":46,"textureId":1,"price":0,"label":null,"restrictionTags":["PARACHUTE"]},{"componentId":5,"drawableId":46,"textureId":2,"price":0,"label":null,"restrictionTags":["PARACHUTE"]},{"componentId":5,"drawableId":46,"textureId":3,"price":0,"label":null,"restrictionTags":["PARACHUTE"]},{"componentId":5,"drawableId":46,"textureId":4,"price":0,"label":null,"restrictionTags":["PARACHUTE"]},{"componentId":5,"drawableId":46,"textureId":5,"price":0,"label":null,"restrictionTags":["PARACHUTE"]},{"componentId":5,"drawableId":46,"textureId":6,"price":0,"label":null,"restrictionTags":["PARACHUTE"]},{"componentId":5,"drawableId":46,"textureId":7,"price":0,"label":null,"restrictionTags":["PARACHUTE"]},{"componentId":5,"drawableId":46,"textureId":8,"price":0,"label":null,"restrictionTags":["PARACHUTE"]},{"componentId":5,"drawableId":46,"textureId":9,"price":0,"label":null,"restrictionTags":["PARACHUTE"]},{"componentId":5,"drawableId":46,"textureId":10,"price":0,"label":null,"restrictionTags":["PARACHUTE"]},{"componentId":5,"drawableId":46,"textureId":11,"price":0,"label":null,"restrictionTags":["PARACHUTE"]},{"componentId":5,"drawableId":46,"textureId":12,"price":0,"label":null,"restrictionTags":["PARACHUTE"]},{"componentId":5,"drawableId":46,"textureId":13,"price":0,"label":null,"restrictionTags":["PARACHUTE"]},{"componentId":5,"drawableId":46,"textureId":14,"price":0,"label":null,"restrictionTags":["PARACHUTE"]},{"componentId":5,"drawableId":46,"textureId":15,"price":0,"label":null,"restrictionTags":["PARACHUTE"]},{"componentId":5,"drawableId":46,"textureId":16,"price":0,"label":null,"restrictionTags":["PARACHUTE"]},{"componentId":5,"drawableId":46,"textureId":17,"price":0,"label":null,"restrictionTags":["PARACHUTE"]},{"componentId":5,"drawableId":46,"textureId":18,"price":0,"label":null,"restrictionTags":["PARACHUTE"]},{"componentId":5,"drawableId":46,"textureId":19,"price":0,"label":null,"restrictionTags":["PARACHUTE"]},{"componentId":5,"drawableId":46,"textureId":20,"price":0,"label":null,"restrictionTags":["PARACHUTE"]},{"componentId":5,"drawableId":46,"textureId":21,"price":0,"label":null,"restrictionTags":["PARACHUTE"]},{"componentId":5,"drawableId":46,"textureId":22,"price":0,"label":null,"restrictionTags":["PARACHUTE"]},{"componentId":5,"drawableId":46,"textureId":23,"price":0,"label":null,"restrictionTags":["PARACHUTE"]},{"componentId":5,"drawableId":46,"textureId":24,"price":0,"label":null,"restrictionTags":["PARACHUTE"]},{"componentId":5,"drawableId":46,"textureId":25,"price":0,"label":null,"restrictionTags":["PARACHUTE"]},{"componentId":5,"drawableId":47,"textureId":0,"price":0,"label":null,"restrictionTags":["PARACHUTE"]},{"componentId":5,"drawableId":47,"textureId":1,"price":0,"label":null,"restrictionTags":["PARACHUTE"]},{"componentId":5,"drawableId":47,"textureId":2,"price":0,"label":null,"restrictionTags":["PARACHUTE"]},{"componentId":5,"drawableId":47,"textureId":3,"price":0,"label":null,"restrictionTags":["PARACHUTE"]},{"componentId":5,"drawableId":47,"textureId":4,"price":0,"label":null,"restrictionTags":["PARACHUTE"]},{"componentId":5,"drawableId":48,"textureId":0,"price":0,"label":null,"restrictionTags":["PARACHUTE"]},{"componentId":5,"drawableId":48,"textureId":1,"price":0,"label":null,"restrictionTags":["PARACHUTE"]},{"componentId":5,"drawableId":48,"textureId":2,"price":0,"label":null,"restrictionTags":["PARACHUTE"]},{"componentId":5,"drawableId":48,"textureId":3,"price":0,"label":null,"restrictionTags":["PARACHUTE"]},{"componentId":5,"drawableId":48,"textureId":4,"price":0,"label":null,"restrictionTags":["PARACHUTE"]},{"componentId":5,"drawableId":48,"textureId":5,"price":0,"label":null,"restrictionTags":["PARACHUTE"]},{"componentId":5,"drawableId":48,"textureId":6,"price":0,"label":null,"restrictionTags":["PARACHUTE"]},{"componentId":5,"drawableId":48,"textureId":7,"price":0,"label":null,"restrictionTags":["PARACHUTE"]},{"componentId":5,"drawableId":48,"textureId":8,"price":0,"label":null,"restrictionTags":["PARACHUTE"]},{"componentId":5,"drawableId":48,"textureId":9,"price":0,"label":null,"restrictionTags":["PARACHUTE"]},{"componentId":5,"drawableId":48,"textureId":10,"price":0,"label":null,"restrictionTags":["PARACHUTE"]},{"componentId":5,"drawableId":48,"textureId":11,"price":0,"label":null,"restrictionTags":["PARACHUTE"]},{"componentId":5,"drawableId":48,"textureId":12,"price":0,"label":null,"restrictionTags":["PARACHUTE"]},{"componentId":5,"drawableId":48,"textureId":13,"price":0,"label":null,"restrictionTags":["PARACHUTE"]},{"componentId":5,"drawableId":48,"textureId":14,"price":0,"label":null,"restrictionTags":["PARACHUTE"]},{"componentId":5,"drawableId":48,"textureId":15,"price":0,"label":null,"restrictionTags":["PARACHUTE"]},{"componentId":5,"drawableId":48,"textureId":16,"price":0,"label":null,"restrictionTags":["PARACHUTE"]},{"componentId":5,"drawableId":48,"textureId":17,"price":0,"label":null,"restrictionTags":["PARACHUTE"]},{"componentId":5,"drawableId":48,"textureId":18,"price":0,"label":null,"restrictionTags":["PARACHUTE"]},{"componentId":5,"drawableId":48,"textureId":19,"price":0,"label":null,"restrictionTags":["PARACHUTE"]},{"componentId":5,"drawableId":48,"textureId":20,"price":0,"label":null,"restrictionTags":["PARACHUTE"]},{"componentId":5,"drawableId":48,"textureId":21,"price":0,"label":null,"restrictionTags":["PARACHUTE"]},{"componentId":5,"drawableId":48,"textureId":22,"price":0,"label":null,"restrictionTags":["PARACHUTE"]},{"componentId":5,"drawableId":48,"textureId":23,"price":0,"label":null,"restrictionTags":["PARACHUTE"]},{"componentId":5,"drawableId":48,"textureId":24,"price":0,"label":null,"restrictionTags":["PARACHUTE"]},{"componentId":5,"drawableId":48,"textureId":25,"price":0,"label":null,"restrictionTags":["PARACHUTE"]},{"componentId":5,"drawableId":49,"textureId":0,"price":0,"label":null,"restrictionTags":["PARACHUTE"]},{"componentId":5,"drawableId":50,"textureId":0,"price":0,"label":null,"restrictionTags":["PARACHUTE"]},{"componentId":5,"drawableId":50,"textureId":1,"price":0,"label":null,"restrictionTags":["PARACHUTE"]},{"componentId":5,"drawableId":50,"textureId":2,"price":0,"label":null,"restrictionTags":["PARACHUTE"]},{"componentId":5,"drawableId":50,"textureId":3,"price":0,"label":null,"restrictionTags":["PARACHUTE"]},{"componentId":5,"drawableId":50,"textureId":4,"price":0,"label":null,"restrictionTags":["PARACHUTE"]},{"componentId":5,"drawableId":50,"textureId":5,"price":0,"label":null,"restrictionTags":["PARACHUTE"]},{"componentId":5,"drawableId":50,"textureId":6,"price":0,"label":null,"restrictionTags":["PARACHUTE"]},{"componentId":5,"drawableId":50,"textureId":7,"price":0,"label":null,"restrictionTags":["PARACHUTE"]},{"componentId":5,"drawableId":50,"textureId":8,"price":0,"label":null,"restrictionTags":["PARACHUTE"]},{"componentId":5,"drawableId":50,"textureId":9,"price":0,"label":null,"restrictionTags":["PARACHUTE"]},{"componentId":5,"drawableId":51,"textureId":0,"price":0,"label":null,"restrictionTags":null},{"componentId":5,"drawableId":51,"textureId":1,"price":0,"label":null,"restrictionTags":null},{"componentId":5,"drawableId":52,"textureId":0,"price":0,"label":null,"restrictionTags":null},{"componentId":5,"drawableId":52,"textureId":1,"price":0,"label":null,"restrictionTags":null},{"componentId":5,"drawableId":53,"textureId":0,"price":0,"label":null,"restrictionTags":null},{"componentId":5,"drawableId":53,"textureId":1,"price":0,"label":null,"restrictionTags":null},{"componentId":5,"drawableId":54,"textureId":0,"price":0,"label":null,"restrictionTags":null},{"componentId":5,"drawableId":54,"textureId":1,"price":0,"label":null,"restrictionTags":null},{"componentId":5,"drawableId":55,"textureId":0,"price":0,"label":null,"restrictionTags":null},{"componentId":5,"drawableId":55,"textureId":1,"price":0,"label":null,"restrictionTags":null},{"componentId":5,"drawableId":56,"textureId":0,"price":0,"label":null,"restrictionTags":null},{"componentId":5,"drawableId":56,"textureId":1,"price":0,"label":null,"restrictionTags":null},{"componentId":5,"drawableId":57,"textureId":0,"price":0,"label":null,"restrictionTags":null},{"componentId":5,"drawableId":57,"textureId":1,"price":0,"label":null,"restrictionTags":null},{"componentId":5,"drawableId":58,"textureId":0,"price":0,"label":null,"restrictionTags":null},{"componentId":5,"drawableId":58,"textureId":1,"price":0,"label":null,"restrictionTags":null},{"componentId":5,"drawableId":59,"textureId":0,"price":0,"label":null,"restrictionTags":null},{"componentId":5,"drawableId":59,"textureId":1,"price":0,"label":null,"restrictionTags":null},{"componentId":5,"drawableId":60,"textureId":0,"price":0,"label":null,"restrictionTags":null},{"componentId":5,"drawableId":60,"textureId":1,"price":0,"label":null,"restrictionTags":null},{"componentId":5,"drawableId":61,"textureId":0,"price":0,"label":null,"restrictionTags":null},{"componentId":5,"drawableId":61,"textureId":1,"price":0,"label":null,"restrictionTags":null},{"componentId":5,"drawableId":62,"textureId":0,"price":0,"label":null,"restrictionTags":["DUFFEL_BAG"]},{"componentId":5,"drawableId":62,"textureId":1,"price":0,"label":null,"restrictionTags":["DUFFEL_BAG"]},{"componentId":5,"drawableId":62,"textureId":2,"price":0,"label":null,"restrictionTags":["DUFFEL_BAG"]},{"componentId":5,"drawableId":62,"textureId":3,"price":0,"label":null,"restrictionTags":["DUFFEL_BAG"]},{"componentId":5,"drawableId":62,"textureId":4,"price":0,"label":null,"restrictionTags":["DUFFEL_BAG"]},{"componentId":5,"drawableId":62,"textureId":5,"price":0,"label":null,"restrictionTags":["DUFFEL_BAG"]},{"componentId":5,"drawableId":62,"textureId":6,"price":0,"label":null,"restrictionTags":["DUFFEL_BAG"]},{"componentId":5,"drawableId":62,"textureId":7,"price":0,"label":null,"restrictionTags":["DUFFEL_BAG"]},{"componentId":5,"drawableId":62,"textureId":8,"price":0,"label":null,"restrictionTags":["DUFFEL_BAG"]},{"componentId":5,"drawableId":62,"textureId":9,"price":0,"label":null,"restrictionTags":["DUFFEL_BAG"]},{"componentId":5,"drawableId":62,"textureId":10,"price":0,"label":null,"restrictionTags":["DUFFEL_BAG"]},{"componentId":5,"drawableId":62,"textureId":11,"price":0,"label":null,"restrictionTags":["DUFFEL_BAG"]},{"componentId":5,"drawableId":62,"textureId":12,"price":0,"label":null,"restrictionTags":["DUFFEL_BAG"]},{"componentId":5,"drawableId":62,"textureId":13,"price":0,"label":null,"restrictionTags":["DUFFEL_BAG"]},{"componentId":5,"drawableId":62,"textureId":14,"price":0,"label":null,"restrictionTags":["DUFFEL_BAG"]},{"componentId":5,"drawableId":62,"textureId":15,"price":0,"label":null,"restrictionTags":["DUFFEL_BAG"]},{"componentId":5,"drawableId":62,"textureId":16,"price":0,"label":null,"restrictionTags":["DUFFEL_BAG"]},{"componentId":5,"drawableId":62,"textureId":17,"price":0,"label":null,"restrictionTags":["DUFFEL_BAG"]},{"componentId":5,"drawableId":62,"textureId":18,"price":0,"label":null,"restrictionTags":["DUFFEL_BAG"]},{"componentId":5,"drawableId":62,"textureId":19,"price":0,"label":null,"restrictionTags":["DUFFEL_BAG"]},{"componentId":5,"drawableId":62,"textureId":20,"price":0,"label":null,"restrictionTags":["DUFFEL_BAG"]},{"componentId":5,"drawableId":62,"textureId":21,"price":0,"label":null,"restrictionTags":["DUFFEL_BAG"]},{"componentId":5,"drawableId":62,"textureId":22,"price":0,"label":null,"restrictionTags":["DUFFEL_BAG"]},{"componentId":5,"drawableId":62,"textureId":23,"price":0,"label":null,"restrictionTags":["DUFFEL_BAG"]},{"componentId":5,"drawableId":62,"textureId":24,"price":0,"label":null,"restrictionTags":["DUFFEL_BAG"]},{"componentId":5,"drawableId":62,"textureId":25,"price":0,"label":null,"restrictionTags":["DUFFEL_BAG"]},{"componentId":5,"drawableId":63,"textureId":0,"price":0,"label":null,"restrictionTags":["DUFFEL_BAG"]},{"componentId":5,"drawableId":63,"textureId":1,"price":0,"label":null,"restrictionTags":["DUFFEL_BAG"]},{"componentId":5,"drawableId":63,"textureId":2,"price":0,"label":null,"restrictionTags":["DUFFEL_BAG"]},{"componentId":5,"drawableId":63,"textureId":3,"price":0,"label":null,"restrictionTags":["DUFFEL_BAG"]},{"componentId":5,"drawableId":63,"textureId":4,"price":0,"label":null,"restrictionTags":["DUFFEL_BAG"]},{"componentId":5,"drawableId":63,"textureId":5,"price":0,"label":null,"restrictionTags":["DUFFEL_BAG"]},{"componentId":5,"drawableId":63,"textureId":6,"price":0,"label":null,"restrictionTags":["DUFFEL_BAG"]},{"componentId":5,"drawableId":63,"textureId":7,"price":0,"label":null,"restrictionTags":["DUFFEL_BAG"]},{"componentId":5,"drawableId":63,"textureId":8,"price":0,"label":null,"restrictionTags":["DUFFEL_BAG"]},{"componentId":5,"drawableId":63,"textureId":9,"price":0,"label":null,"restrictionTags":["DUFFEL_BAG"]},{"componentId":5,"drawableId":63,"textureId":10,"price":0,"label":null,"restrictionTags":["DUFFEL_BAG"]},{"componentId":5,"drawableId":63,"textureId":11,"price":0,"label":null,"restrictionTags":["DUFFEL_BAG"]},{"componentId":5,"drawableId":63,"textureId":12,"price":0,"label":null,"restrictionTags":["DUFFEL_BAG"]},{"componentId":5,"drawableId":63,"textureId":13,"price":0,"label":null,"restrictionTags":["DUFFEL_BAG"]},{"componentId":5,"drawableId":63,"textureId":14,"price":0,"label":null,"restrictionTags":["DUFFEL_BAG"]},{"componentId":5,"drawableId":63,"textureId":15,"price":0,"label":null,"restrictionTags":["DUFFEL_BAG"]},{"componentId":5,"drawableId":63,"textureId":16,"price":0,"label":null,"restrictionTags":["DUFFEL_BAG"]},{"componentId":5,"drawableId":63,"textureId":17,"price":0,"label":null,"restrictionTags":["DUFFEL_BAG"]},{"componentId":5,"drawableId":63,"textureId":18,"price":0,"label":null,"restrictionTags":["DUFFEL_BAG"]},{"componentId":5,"drawableId":63,"textureId":19,"price":0,"label":null,"restrictionTags":["DUFFEL_BAG"]},{"componentId":5,"drawableId":63,"textureId":20,"price":0,"label":null,"restrictionTags":["DUFFEL_BAG"]},{"componentId":5,"drawableId":63,"textureId":21,"price":0,"label":null,"restrictionTags":["DUFFEL_BAG"]},{"componentId":5,"drawableId":63,"textureId":22,"price":0,"label":null,"restrictionTags":["DUFFEL_BAG"]},{"componentId":5,"drawableId":63,"textureId":23,"price":0,"label":null,"restrictionTags":["DUFFEL_BAG"]},{"componentId":5,"drawableId":63,"textureId":24,"price":0,"label":null,"restrictionTags":["DUFFEL_BAG"]},{"componentId":5,"drawableId":63,"textureId":25,"price":0,"label":null,"restrictionTags":["DUFFEL_BAG"]},{"componentId":5,"drawableId":64,"textureId":0,"price":0,"label":null,"restrictionTags":["DUFFEL_BAG"]},{"componentId":5,"drawableId":64,"textureId":1,"price":0,"label":null,"restrictionTags":["DUFFEL_BAG"]},{"componentId":5,"drawableId":64,"textureId":2,"price":0,"label":null,"restrictionTags":["DUFFEL_BAG"]},{"componentId":5,"drawableId":64,"textureId":3,"price":0,"label":null,"restrictionTags":["DUFFEL_BAG"]},{"componentId":5,"drawableId":64,"textureId":4,"price":0,"label":null,"restrictionTags":["DUFFEL_BAG"]},{"componentId":5,"drawableId":64,"textureId":5,"price":0,"label":null,"restrictionTags":["DUFFEL_BAG"]},{"componentId":5,"drawableId":64,"textureId":6,"price":0,"label":null,"restrictionTags":["DUFFEL_BAG"]},{"componentId":5,"drawableId":64,"textureId":7,"price":0,"label":null,"restrictionTags":["DUFFEL_BAG"]},{"componentId":5,"drawableId":64,"textureId":8,"price":0,"label":null,"restrictionTags":["DUFFEL_BAG"]},{"componentId":5,"drawableId":64,"textureId":9,"price":0,"label":null,"restrictionTags":["DUFFEL_BAG"]},{"componentId":5,"drawableId":64,"textureId":10,"price":0,"label":null,"restrictionTags":["DUFFEL_BAG"]},{"componentId":5,"drawableId":64,"textureId":11,"price":0,"label":null,"restrictionTags":["DUFFEL_BAG"]},{"componentId":5,"drawableId":64,"textureId":12,"price":0,"label":null,"restrictionTags":["DUFFEL_BAG"]},{"componentId":5,"drawableId":64,"textureId":13,"price":0,"label":null,"restrictionTags":["DUFFEL_BAG"]},{"componentId":5,"drawableId":64,"textureId":14,"price":0,"label":null,"restrictionTags":["DUFFEL_BAG"]},{"componentId":5,"drawableId":64,"textureId":15,"price":0,"label":null,"restrictionTags":["DUFFEL_BAG"]},{"componentId":5,"drawableId":64,"textureId":16,"price":0,"label":null,"restrictionTags":["DUFFEL_BAG"]},{"componentId":5,"drawableId":64,"textureId":17,"price":0,"label":null,"restrictionTags":["DUFFEL_BAG"]},{"componentId":5,"drawableId":64,"textureId":18,"price":0,"label":null,"restrictionTags":["DUFFEL_BAG"]},{"componentId":5,"drawableId":64,"textureId":19,"price":0,"label":null,"restrictionTags":["DUFFEL_BAG"]},{"componentId":5,"drawableId":64,"textureId":20,"price":0,"label":null,"restrictionTags":["DUFFEL_BAG"]},{"componentId":5,"drawableId":64,"textureId":21,"price":0,"label":null,"restrictionTags":["DUFFEL_BAG"]},{"componentId":5,"drawableId":64,"textureId":22,"price":0,"label":null,"restrictionTags":["DUFFEL_BAG"]},{"componentId":5,"drawableId":64,"textureId":23,"price":0,"label":null,"restrictionTags":["DUFFEL_BAG"]},{"componentId":5,"drawableId":64,"textureId":24,"price":0,"label":null,"restrictionTags":["DUFFEL_BAG"]},{"componentId":5,"drawableId":64,"textureId":25,"price":0,"label":null,"restrictionTags":["DUFFEL_BAG"]},{"componentId":5,"drawableId":65,"textureId":0,"price":0,"label":null,"restrictionTags":["DUFFEL_BAG"]},{"componentId":5,"drawableId":65,"textureId":1,"price":0,"label":null,"restrictionTags":["DUFFEL_BAG"]},{"componentId":5,"drawableId":65,"textureId":2,"price":0,"label":null,"restrictionTags":["DUFFEL_BAG"]},{"componentId":5,"drawableId":65,"textureId":3,"price":0,"label":null,"restrictionTags":["DUFFEL_BAG"]},{"componentId":5,"drawableId":65,"textureId":4,"price":0,"label":null,"restrictionTags":["DUFFEL_BAG"]},{"componentId":5,"drawableId":65,"textureId":5,"price":0,"label":null,"restrictionTags":["DUFFEL_BAG"]},{"componentId":5,"drawableId":65,"textureId":6,"price":0,"label":null,"restrictionTags":["DUFFEL_BAG"]},{"componentId":5,"drawableId":65,"textureId":7,"price":0,"label":null,"restrictionTags":["DUFFEL_BAG"]},{"componentId":5,"drawableId":65,"textureId":8,"price":0,"label":null,"restrictionTags":["DUFFEL_BAG"]},{"componentId":5,"drawableId":65,"textureId":9,"price":0,"label":null,"restrictionTags":["DUFFEL_BAG"]},{"componentId":5,"drawableId":65,"textureId":10,"price":0,"label":null,"restrictionTags":["DUFFEL_BAG"]},{"componentId":5,"drawableId":65,"textureId":11,"price":0,"label":null,"restrictionTags":["DUFFEL_BAG"]},{"componentId":5,"drawableId":65,"textureId":12,"price":0,"label":null,"restrictionTags":["DUFFEL_BAG"]},{"componentId":5,"drawableId":65,"textureId":13,"price":0,"label":null,"restrictionTags":["DUFFEL_BAG"]},{"componentId":5,"drawableId":65,"textureId":14,"price":0,"label":null,"restrictionTags":["DUFFEL_BAG"]},{"componentId":5,"drawableId":65,"textureId":15,"price":0,"label":null,"restrictionTags":["DUFFEL_BAG"]},{"componentId":5,"drawableId":65,"textureId":16,"price":0,"label":null,"restrictionTags":["DUFFEL_BAG"]},{"componentId":5,"drawableId":65,"textureId":17,"price":0,"label":null,"restrictionTags":["DUFFEL_BAG"]},{"componentId":5,"drawableId":65,"textureId":18,"price":0,"label":null,"restrictionTags":["DUFFEL_BAG"]},{"componentId":5,"drawableId":65,"textureId":19,"price":0,"label":null,"restrictionTags":["DUFFEL_BAG"]},{"componentId":5,"drawableId":65,"textureId":20,"price":0,"label":null,"restrictionTags":["DUFFEL_BAG"]},{"componentId":5,"drawableId":65,"textureId":21,"price":0,"label":null,"restrictionTags":["DUFFEL_BAG"]},{"componentId":5,"drawableId":65,"textureId":22,"price":0,"label":null,"restrictionTags":["DUFFEL_BAG"]},{"componentId":5,"drawableId":65,"textureId":23,"price":0,"label":null,"restrictionTags":["DUFFEL_BAG"]},{"componentId":5,"drawableId":65,"textureId":24,"price":0,"label":null,"restrictionTags":["DUFFEL_BAG"]},{"componentId":5,"drawableId":65,"textureId":25,"price":0,"label":null,"restrictionTags":["DUFFEL_BAG"]}]